README.md
setup.py
pydouz/__init__.py
pydouz/__main__.py
pydouz/ast.py
pydouz/cmdline.py
pydouz/codegen.py
pydouz/common.py
pydouz/convention.py
pydouz/driver.py
pydouz/error.py
pydouz/parser.py
pydouz/tokenization.py
pydouz.egg-info/PKG-INFO
pydouz.egg-info/SOURCES.txt
pydouz.egg-info/dependency_links.txt
pydouz.egg-info/entry_points.txt
pydouz.egg-info/requires.txt
pydouz.egg-info/top_level.txt