Metadata-Version: 2.1
Name: pydouz
Version: 0.1.2
Summary: Douz is an experimental language for embedded and math.
Home-page: https://github.com/mohanson/pydouz
Author: mohanson
Author-email: mohanson@outlook.com
License: WTFPL
Platform: UNKNOWN
